GPMM/FUWMM.py
GPMM/FWMM.py
GPMM/UWMM.py
GPMM/WMM.py
GPMM/__init__.py
GPMM-0.1.2.dist-info/METADATA
GPMM-0.1.2.dist-info/WHEEL
GPMM-0.1.2.dist-info/top_level.txt
GPMM-0.1.2.dist-info/RECORD
