Metadata-Version: 2.1
Name: GPMM
Version: 0.1.2
Summary: Collection of generalized p-mean models with classic, fuzzy and unweighted approach
Home-page: https://github.com/Aaron-AALG/GPMM
Author: Aaron Lopez-Garcia
Author-email: aaron.lopez@uv.es
License: MIT
Download-URL: https://github.com/Aaron-AALG/GPMM/releases/tag/GPMM_0.1.2
Platform: UNKNOWN
Classifier: Programming Language :: Python :: 3.8
Classifier: License :: OSI Approved :: MIT License
Requires-Dist: numpy (>=1.19)
Requires-Dist: scipy (>=1.6.3)
